backupchan_server/__init__.py
backupchan_server/models.py
backupchan_server/nameformat.py
backupchan_server/utility.py
backupchan_server_lib-0.2.0.dist-info/licenses/LICENSE
backupchan_server_lib-0.2.0.dist-info/METADATA
backupchan_server_lib-0.2.0.dist-info/WHEEL
backupchan_server_lib-0.2.0.dist-info/top_level.txt
backupchan_server_lib-0.2.0.dist-info/RECORD
