Metadata-Version: 2.4
Name: backupchan-server-lib
Version: 0.2.0
Summary: Utilities and structures used by the Backup-chan server.
Author-email: Moltony <koronavirusnyj@gmail.com>
License: BSD-3-Clause
Project-URL: Homepage, https://github.com/Backupchan/server-lib
Project-URL: Repository, https://github.com/Backupchan/server-lib.git
Project-URL: Issues, https://github.com/Backupchan/server-lib/issues
Project-URL: Changelog, https://github.com/Backupchan/server-lib/blob/main/CHANGELOG.md
Classifier: Development Status :: 5 - Production/Stable
Classifier: License :: OSI Approved :: BSD License
Classifier: Natural Language :: English
Classifier: Operating System :: OS Independent
Classifier: Programming Language :: Python :: 3 :: Only
Classifier: Topic :: System :: Archiving :: Backup
Classifier: Topic :: Software Development :: Libraries
Classifier: Typing :: Typed
License-File: LICENSE
Provides-Extra: dev
Requires-Dist: pytest; extra == "dev"
Dynamic: license-file
